Metadata-Version: 1.0
Name: toil-scripts
Version: 2.1.0a1.dev681
Summary: A repository of genomic workflows developed by the UCSC Computational Genomics lab 
Home-page: https://github.com/BD2KGenomics/toil-scripts
Author: UCSC Computational Genomics Lab
Author-email: cgl-toil@googlegroups.com
License: UNKNOWN
Platform: UNKNOWN
